geonexus/__init__.py
geonexus/common.py
geonexus/foliumap.py
geonexus/geonexus.py
geonexus-0.1.0.dist-info/licenses/LICENSE
geonexus-0.1.0.dist-info/METADATA
geonexus-0.1.0.dist-info/WHEEL
geonexus-0.1.0.dist-info/entry_points.txt
geonexus-0.1.0.dist-info/top_level.txt
geonexus-0.1.0.dist-info/RECORD
